ewoks3dxrd/__init__.py
ewoks3dxrd/filtering.py
ewoks3dxrd/grain_visualizer.py
ewoks3dxrd/io.py
ewoks3dxrd/models.py
ewoks3dxrd/sub_process_task_mixin.py
ewoks3dxrd/tmp_files.py
ewoks3dxrd/tqdm_progress_callback.py
ewoks3dxrd/utils.py
ewoks3dxrd/grid_indexing/__init__.py
ewoks3dxrd/grid_indexing/grid_indexer_worker_script.py
ewoks3dxrd/grid_indexing/indexing.py
ewoks3dxrd/grid_indexing/make_grain_map_worker_script.py
ewoks3dxrd/nexus/__init__.py
ewoks3dxrd/nexus/grains.py
ewoks3dxrd/nexus/parameters.py
ewoks3dxrd/nexus/peaks.py
ewoks3dxrd/nexus/utils.py
ewoks3dxrd/segmentation/__init__.py
ewoks3dxrd/segmentation/gaussian.py
ewoks3dxrd/segmentation/lima.py
ewoks3dxrd/tasks/__init__.py
ewoks3dxrd/tasks/detector_spatial_correction.py
ewoks3dxrd/tasks/filter_by_index.py
ewoks3dxrd/tasks/filter_by_intensity.py
ewoks3dxrd/tasks/filter_by_lattice.py
ewoks3dxrd/tasks/geometry_transformation.py
ewoks3dxrd/tasks/grid_index_grains.py
ewoks3dxrd/tasks/grid_index_grains_sub_process.py
ewoks3dxrd/tasks/index_grains.py
ewoks3dxrd/tasks/make_grain_map.py
ewoks3dxrd/tasks/make_grain_map_sub_process.py
ewoks3dxrd/tasks/segment_scan.py
ewoks3dxrd/tests/__init__.py
ewoks3dxrd/tests/conftest.py
ewoks3dxrd/tests/test_3dxrd_workflow.py
ewoks3dxrd/tests/test_filter_by_index.py
ewoks3dxrd/tests/test_filter_by_intensity.py
ewoks3dxrd/tests/test_filter_by_lattice.py
ewoks3dxrd/tests/test_gaussian_segmentation.py
ewoks3dxrd/tests/test_geometry_transformation.py
ewoks3dxrd/tests/test_grid_indexing.py
ewoks3dxrd/tests/test_id03_3dxrd_workflow.py
ewoks3dxrd/tests/test_indexing.py
ewoks3dxrd/tests/test_lima_segmentation.py
ewoks3dxrd/tests/test_map_grains.py
ewoks3dxrd/tests/test_utils.py
ewoks3dxrd/tests/canvas/test_fit_geometry.py
ewoks3dxrd/tests/canvas/test_image_file_generator.py
ewoks3dxrd/tests/canvas/test_refine_grains.py
ewoks3dxrd/tests/canvas/test_segmenter_view.py
ewoks3dxrd-1.0.0.dist-info/licenses/LICENSE.md
orangecontrib/ewoks3dxrd/__init__.py
orangecontrib/ewoks3dxrd/detector_correction.py
ewoks3dxrd-1.0.0.dist-info/METADATA
ewoks3dxrd-1.0.0.dist-info/WHEEL
ewoks3dxrd-1.0.0.dist-info/entry_points.txt
ewoks3dxrd-1.0.0.dist-info/top_level.txt
ewoks3dxrd-1.0.0.dist-info/RECORD
