Metadata-Version: 2.4
Name: ewoks3dxrd
Version: 1.0.0
Summary: Ewoks 3DXRD workflows
Author-email: ESRF <dau-pydev@esrf.fr>
License: # MIT License
Project-URL: Homepage, https://gitlab.esrf.fr/workflow/ewoksapps/ewoks3dxrd/
Project-URL: Documentation, https://ewoks3dxrd.readthedocs.io/
Project-URL: Repository, https://gitlab.esrf.fr/workflow/ewoksapps/ewoks3dxrd/
Project-URL: Issues, https://gitlab.esrf.fr/workflow/ewoksapps/ewoks3dxrd/issues
Project-URL: Changelog, https://gitlab.esrf.fr/workflow/ewoksapps/ewoks3dxrd/-/blob/main/CHANGELOG.md
Keywords: orange3 add-on,ewoks
Classifier: Intended Audience :: Science/Research
Classifier: License :: OSI Approved :: MIT License
Classifier: Programming Language :: Python :: 3
Requires-Python: >=3.10
License-File: LICENSE.md
Requires-Dist: ewoksorange>=3.2.1
Requires-Dist: ewokscore>=1.5.0
Requires-Dist: pydantic>=2
Requires-Dist: silx>=2.2.0
Requires-Dist: qtawesome
Requires-Dist: pyFAI==2025.3.0
Requires-Dist: ImageD11==2.1.3
Requires-Dist: PyOpenGL>=3.1.10
Requires-Dist: bslz4-to-sparse>=0.0.16
Provides-Extra: full
Requires-Dist: pyqt5; extra == "full"
Provides-Extra: test
Requires-Dist: ewoks3dxrd[full]; extra == "test"
Requires-Dist: pytest>=8; extra == "test"
Provides-Extra: dev
Requires-Dist: ewoks3dxrd[test]; extra == "dev"
Requires-Dist: black>=25; extra == "dev"
Requires-Dist: flake8>=7; extra == "dev"
Provides-Extra: doc
Requires-Dist: ewoks3dxrd[test]; extra == "doc"
Requires-Dist: sphinx>=8; extra == "doc"
Requires-Dist: pydata_sphinx_theme; extra == "doc"
Requires-Dist: myst-parser; extra == "doc"
Requires-Dist: ewokssphinx>=1.0.0; extra == "doc"
Requires-Dist: sphinxcontrib-mermaid; extra == "doc"
Requires-Dist: sphinx-argparse; extra == "doc"
Dynamic: license-file
